byusi_ulid-1.1.3.dist-info/licenses/LICENSE
ulid/__init__.py
ulid/cli.py
ulid/core.py
byusi_ulid-1.1.3.dist-info/METADATA
byusi_ulid-1.1.3.dist-info/WHEEL
byusi_ulid-1.1.3.dist-info/entry_points.txt
byusi_ulid-1.1.3.dist-info/top_level.txt
byusi_ulid-1.1.3.dist-info/RECORD
